LICENSE
README.rst
setup.cfg
setup.py
cryptopher/__init__.py
cryptopher.egg-info/PKG-INFO
cryptopher.egg-info/SOURCES.txt
cryptopher.egg-info/dependency_links.txt
cryptopher.egg-info/requires.txt
cryptopher.egg-info/top_level.txt
cryptopher/analysis/__init__.py
cryptopher/analysis/back_test.py
cryptopher/collect/__init__.py
cryptopher/collect/get_binance_data.py
cryptopher/indicator/__init__.py
cryptopher/indicator/rsi.py
cryptopher/painter/__init__.py
cryptopher/painter/drawer.py