Metadata-Version: 2.1
Name: cryptopher
Version: 0.0.0
Summary: Cryptopher library
Home-page: https://github.com/PesseCanoe/cryptopher
Author: Cryptopher
Author-email: cryptopher.trader@gmail.com
License: MIT
Download-URL: https://github.com/PesseCanoe/cryptopher/archive/v0_0_0.tar.gz
Platform: UNKNOWN
Requires-Python: >=3.6
License-File: LICENSE
